CD/CD.py
CD/__init__.py
CI/CI.py
CI/__init__.py
common/__init__.py
common/file_path.py
common/init_yaml.py
conf/__init__.py
FlawlessCICD-0.2.0.dist-info/METADATA
FlawlessCICD-0.2.0.dist-info/WHEEL
FlawlessCICD-0.2.0.dist-info/top_level.txt
FlawlessCICD-0.2.0.dist-info/RECORD
